[
  {
    "id": "1.0.1",
    "identifier": "swish.1.0.1",
    "inherit": "",
    "name": "Example 1.0.1.",
    "code": "1.0.1.pl",
    "query": "?-connected(bond_street,Y,L). ?-connected(X,piccadilly_circus,L). ?-connected(X,Y,piccadilly). ?-connected(X,Y,L),connected(Y,Z,L)."
  },
  {
    "id": "1.0.2",
    "identifier": "swish.1.0.2",
    "inherit": "",
    "name": "Example 1.0.2.",
    "code": "1.0.2.pl",
    "query": "?-nearby(bond_street,Y). ?-nearby(X,piccadilly_circus). ?-nearby(X,Y). ?-nearby(X,Y),nearby(Y,Z)."
  },
  {
    "id": "1.0.3",
    "identifier": "swish.1.0.3",
    "inherit": "swish.1.0.1",
    "name": "Example 1.0.3.",
    "code": "1.0.3.pl",
    "query": "?-nearby(tottenham_court_road,leicester_square). ?-nearby(tottenham_court_road,W). ?-nearby(X,leicester_square)."
  },
  {
    "id": "1.0.4",
    "identifier": "swish.1.0.4",
    "inherit": "swish.1.0.1",
    "name": "Example 1.0.4.",
    "code": "1.0.4.pl",
    "query": "?-not_too_far(X,Y)."
  },
  {
    "id": "1.1.1",
    "identifier": "swish.1.1.1",
    "inherit": "",
    "name": "Example 1.1.1.",
    "code": "1.1.1.pl",
    "query": "?-reachable(bond_street,Y). ?-reachable(X,green_park). ?-reachable(X,Y)."
  },
  {
    "id": "1.1.2",
    "identifier": "swish.1.1.2",
    "inherit": "swish.1.0.1",
    "name": "Example 1.1.2.",
    "code": "1.1.2.pl",
    "query": "?-reachable(bond_street,Y). ?-reachable(X,green_park). ?-reachable(X,Y)."
  },

  {
    "id": "1.2.1",
    "identifier": "swish.1.2.1",
    "inherit": "swish.1.0.1",
    "name": "Example 1.2.1.",
    "code": "1.2.1.pl",
    "query": "?-reachable(oxford_circus,charing_cross,R)."
  },
  {
    "id": "1.2.2",
    "identifier": "swish.1.2.2",
    "inherit": "swish.1.0.1",
    "name": "Example 1.2.2.",
    "code": "1.2.2.pl",
    "query": "?-reachable(oxford_circus,charing_cross,R)."
  },
  {
    "id": "1.2.2_2",
    "identifier": "swish.1.2.2",
    "inherit": "swish.1.0.1",
    "name": "Example 1.2.2. (ii)",
    "code": "1.2.2_2.pl",
    "query": "?-reachable(oxford_circus,charing_cross,R)."
  },
  {
    "id": "1.2.3",
    "identifier": "swish.1.2.3",
    "inherit": "swish.1.0.1",
    "name": "Example 1.2.3.",
    "code": "1.2.3.pl",
    "query": "?-reachable(oxford_circus,charing_cross,R). ?-reachable(X,charing_cross,[A,B,C,D]). ?-reachable(bond_street,piccadilly_circus,[A,B|L])."
  }
]
